odoo/addons/hr_timesheet_activity_begin_end/README.rst
odoo/addons/hr_timesheet_activity_begin_end/__init__.py
odoo/addons/hr_timesheet_activity_begin_end/__manifest__.py
odoo/addons/hr_timesheet_activity_begin_end/i18n/cs_CZ.po
odoo/addons/hr_timesheet_activity_begin_end/i18n/de.po
odoo/addons/hr_timesheet_activity_begin_end/i18n/es.po
odoo/addons/hr_timesheet_activity_begin_end/i18n/fr.po
odoo/addons/hr_timesheet_activity_begin_end/i18n/hr_timesheet_activity_begin_end.pot
odoo/addons/hr_timesheet_activity_begin_end/i18n/it.po
odoo/addons/hr_timesheet_activity_begin_end/i18n/nl_NL.po
odoo/addons/hr_timesheet_activity_begin_end/models/__init__.py
odoo/addons/hr_timesheet_activity_begin_end/models/account_analytic_line.py
odoo/addons/hr_timesheet_activity_begin_end/readme/CONTRIBUTORS.rst
odoo/addons/hr_timesheet_activity_begin_end/readme/DESCRIPTION.rst
odoo/addons/hr_timesheet_activity_begin_end/static/description/icon.png
odoo/addons/hr_timesheet_activity_begin_end/static/description/index.html
odoo/addons/hr_timesheet_activity_begin_end/tests/__init__.py
odoo/addons/hr_timesheet_activity_begin_end/tests/test_timesheet_begin_end.py
odoo/addons/hr_timesheet_activity_begin_end/views/hr_analytic_timesheet.xml
odoo/addons/hr_timesheet_activity_begin_end/views/hr_timesheet_sheet.xml
odoo13_addon_hr_timesheet_activity_begin_end-13.0.1.0.1.dist-info/METADATA
odoo13_addon_hr_timesheet_activity_begin_end-13.0.1.0.1.dist-info/WHEEL
odoo13_addon_hr_timesheet_activity_begin_end-13.0.1.0.1.dist-info/top_level.txt
odoo13_addon_hr_timesheet_activity_begin_end-13.0.1.0.1.dist-info/RECORD
